pandalytics/__init__.py
pandalytics/agent.py
pandalytics/requirements.txt
pandalytics/shell.py
pandalytics/templates/agent_prompt.py
pandalytics/templates/code_generation_prompt.py
pandalytics/tools.py
pandalytics-0.1.1.dist-info/LICENSE
pandalytics-0.1.1.dist-info/METADATA
pandalytics-0.1.1.dist-info/WHEEL
pandalytics-0.1.1.dist-info/RECORD
