Metadata-Version: 2.1
Name: pandalytics
Version: 0.1.1
Summary: 
Author: Mohit Singh
Author-email: mohwits@gmail.com
Requires-Python: >=3.11,<4.0
Classifier: Programming Language :: Python :: 3
Classifier: Programming Language :: Python :: 3.11
Classifier: Programming Language :: Python :: 3.12
Requires-Dist: anthropic (>=0.26.1,<0.27.0)
Requires-Dist: matplotlib (>=3.9.0,<4.0.0)
Requires-Dist: pandas (>=2.2.2,<3.0.0)
Requires-Dist: python-dotenv (>=1.0.1,<2.0.0)
